setup.py
django_simple_keywords.egg-info/PKG-INFO
django_simple_keywords.egg-info/SOURCES.txt
django_simple_keywords.egg-info/dependency_links.txt
django_simple_keywords.egg-info/top_level.txt
djsimplekeywords/__init__.py