Metadata-Version: 1.0
Name: django-simple-keywords
Version: 0.0.1
Summary: django-simple-keywords
Home-page: https://github.com/lvjiyong/django-simple-keywords
Author: lvjiyong
Author-email: lvjiyong@gmail.com
License: Apache2.0
Platform: any
